django_downtime-1.1.2.dist-info/DESCRIPTION.rst
django_downtime-1.1.2.dist-info/METADATA
django_downtime-1.1.2.dist-info/RECORD
django_downtime-1.1.2.dist-info/WHEEL
django_downtime-1.1.2.dist-info/metadata.json
django_downtime-1.1.2.dist-info/top_level.txt
downtime/__init__.py
downtime/admin.py
downtime/managers.py
downtime/middleware.py
downtime/models.py
downtime/management/__init__.py
downtime/management/commands/__init__.py
downtime/management/commands/downtime_end.py
downtime/management/commands/downtime_start.py
downtime/migrations/0001_initial.py
downtime/migrations/__init__.py
downtime/south_migrations/0001_initial.py
downtime/south_migrations/__init__.py
downtime/templates/downtime/downtime.html
downtime/tests/__init__.py
downtime/tests/factories.py
downtime/tests/test_commands.py
downtime/tests/test_middleware.py
downtime/tests/test_models.py
downtime/tests/test_smoke.py
